[{"athlete":"Michael Phelps","age":23,"country":"United States","year":2008,"date":"24/08/2008","sport":"Swimming","gold":8,"silver":0,"bronze":0,"total":8},
  {"athlete":"Michael Phelps","age":19,"country":"United States","year":2004,"date":"29/08/2004","sport":"Swimming","gold":6,"silver":0,"bronze":2,"total":8},
  {"athlete":"Michael Phelps","age":27,"country":"United States","year":2012,"date":"12/08/2012","sport":"Swimming","gold":4,"silver":2,"bronze":0,"total":6},
  {"athlete":"Anna Svärd-Le Moine","age":32,"country":"Sweden","year":2006,"date":"26/02/2006","sport":"Curling","gold":1,"silver":0,"bronze":0,"total":1},
  {"athlete":"Markku Uusipaavalniemi","age":39,"country":"Finland","year":2006,"date":"26/02/2006","sport":"Curling","gold":0,"silver":1,"bronze":0,"total":1},
  {"athlete":"Don Bartlett","age":41,"country":"Canada","year":2002,"date":"24/02/2002","sport":"Curling","gold":0,"silver":1,"bronze":0,"total":1},
  {"athlete":"Laurence Bidaud","age":33,"country":"Switzerland","year":2002,"date":"24/02/2002","sport":"Curling","gold":0,"silver":1,"bronze":0,"total":1},
  {"athlete":"Flemming Davanger","age":38,"country":"Norway","year":2002,"date":"24/02/2002","sport":"Curling","gold":1,"silver":0,"bronze":0,"total":1},
  {"athlete":"Luzia Ebnöther","age":30,"country":"Switzerland","year":2002,"date":"24/02/2002","sport":"Curling","gold":0,"silver":1,"bronze":0,"total":1},
  {"athlete":"Markus Eggler","age":33,"country":"Switzerland","year":2002,"date":"24/02/2002","sport":"Curling","gold":0,"silver":0,"bronze":1,"total":1},
  {"athlete":"Tanya Frei","age":29,"country":"Switzerland","year":2002,"date":"24/02/2002","sport":"Curling","gold":0,"silver":1,"bronze":0,"total":1},
  {"athlete":"Damian Grichting","age":28,"country":"Switzerland","year":2002,"date":"24/02/2002","sport":"Curling","gold":0,"silver":0,"bronze":1,"total":1},
  {"athlete":"Debbie Knox","age":33,"country":"Great Britain","year":2002,"date":"24/02/2002","sport":"Curling","gold":1,"silver":0,"bronze":0,"total":1},
  {"athlete":"Tina Thompson","age":33,"country":"United States","year":2008,"date":"24/08/2008","sport":"Basketball","gold":1,"silver":0,"bronze":0,"total":1},
  {"athlete":"Nataliya Vodopyanova","age":27,"country":"Russia","year":2008,"date":"24/08/2008","sport":"Basketball","gold":0,"silver":0,"bronze":1,"total":1},
  {"athlete":"Dwyane Wade Jr.","age":26,"country":"United States","year":2008,"date":"24/08/2008","sport":"Basketball","gold":1,"silver":0,"bronze":0,"total":1},
  {"athlete":"Kristi Harrower","age":29,"country":"Australia","year":2004,"date":"29/08/2004","sport":"Basketball","gold":0,"silver":1,"bronze":0,"total":1},
  {"athlete":"Walter Herrmann","age":25,"country":"Argentina","year":2004,"date":"29/08/2004","sport":"Basketball","gold":1,"silver":0,"bronze":0,"total":1},
  {"athlete":"Allen Iverson","age":29,"country":"United States","year":2004,"date":"29/08/2004","sport":"Basketball","gold":0,"silver":0,"bronze":1,"total":1},
  {"athlete":"Lauren Jackson","age":23,"country":"Australia","year":2004,"date":"29/08/2004","sport":"Basketball","gold":0,"silver":1,"bronze":0,"total":1},
  {"athlete":"LeBron James","age":19,"country":"United States","year":2004,"date":"29/08/2004","sport":"Basketball","gold":0,"silver":0,"bronze":1,"total":1},
  {"athlete":"Richard Jefferson","age":24,"country":"United States","year":2004,"date":"29/08/2004","sport":"Basketball","gold":0,"silver":0,"bronze":1,"total":1},
  {"athlete":"Shannon Johnson","age":29,"country":"United States","year":2004,"date":"29/08/2004","sport":"Basketball","gold":1,"silver":0,"bronze":0,"total":1},
  {"athlete":"Mariya Kalmykova","age":30,"country":"Russia","year":2004,"date":"29/08/2004","sport":"Basketball","gold":0,"silver":0,"bronze":1,"total":1},
  {"athlete":"Yelena Karpova","age":24,"country":"Russia","year":2004,"date":"29/08/2004","sport":"Basketball","gold":0,"silver":0,"bronze":1,"total":1},
  {"athlete":"Ilona Korstin","age":24,"country":"Russia","year":2004,"date":"29/08/2004","sport":"Basketball","gold":0,"silver":0,"bronze":1,"total":1},
  {"athlete":"Lisa Leslie","age":32,"country":"United States","year":2004,"date":"29/08/2004","sport":"Basketball","gold":1,"silver":0,"bronze":0,"total":1},
  {"athlete":"Stephon Marbury","age":27,"country":"United States","year":2004,"date":"29/08/2004","sport":"Basketball","gold":0,"silver":0,"bronze":1,"total":1},
  {"athlete":"Denis Marconato","age":29,"country":"Italy","year":2004,"date":"29/08/2004","sport":"Basketball","gold":0,"silver":1,"bronze":0,"total":1},
  {"athlete":"Shawn Marion","age":26,"country":"United States","year":2004,"date":"29/08/2004","sport":"Basketball","gold":0,"silver":0,"bronze":1,"total":1},
  {"athlete":"Michele Mian","age":31,"country":"Italy","year":2004,"date":"29/08/2004","sport":"Basketball","gold":0,"silver":1,"bronze":0,"total":1},
  {"athlete":"Alejandro Ariel Montecchia","age":32,"country":"Argentina","year":2004,"date":"29/08/2004","sport":"Basketball","gold":1,"silver":0,"bronze":0,"total":1},
  {"athlete":"Andrés Nocioni","age":24,"country":"Argentina","year":2004,"date":"29/08/2004","sport":"Basketball","gold":1,"silver":0,"bronze":0,"total":1},
  {"athlete":"Fabricio Oberto","age":31,"country":"Argentina","year":2004,"date":"29/08/2004","sport":"Basketball","gold":1,"silver":0,"bronze":0,"total":1},
  {"athlete":"Lamar Odom","age":24,"country":"United States","year":2004,"date":"29/08/2004","sport":"Basketball","gold":0,"silver":0,"bronze":1,"total":1},
  {"athlete":"Emeka Okafor","age":21,"country":"United States","year":2004,"date":"29/08/2004","sport":"Basketball","gold":0,"silver":0,"bronze":1,"total":1},
  {"athlete":"Irina Osipova","age":23,"country":"Russia","year":2004,"date":"29/08/2004","sport":"Basketball","gold":0,"silver":0,"bronze":1,"total":1},
  {"athlete":"Natalie Porter","age":23,"country":"Australia","year":2004,"date":"29/08/2004","sport":"Basketball","gold":0,"silver":1,"bronze":0,"total":1},
  {"athlete":"Alicia Poto","age":26,"country":"Australia","year":2004,"date":"29/08/2004","sport":"Basketball","gold":0,"silver":1,"bronze":0,"total":1},
  {"athlete":"Gianmarco Pozzecco","age":31,"country":"Italy","year":2004,"date":"29/08/2004","sport":"Basketball","gold":0,"silver":1,"bronze":0,"total":1},
  {"athlete":"Nikola Radulovic","age":31,"country":"Italy","year":2004,"date":"29/08/2004","sport":"Basketball","gold":0,"silver":1,"bronze":0,"total":1},
  {"athlete":"Oksana Rakhmatulina","age":27,"country":"Russia","year":2004,"date":"29/08/2004","sport":"Basketball","gold":0,"silver":0,"bronze":1,"total":1},
  {"athlete":"Alex Righetti","age":27,"country":"Italy","year":2004,"date":"29/08/2004","sport":"Basketball","gold":0,"silver":1,"bronze":0,"total":1},
  {"athlete":"Ruth Riley","age":24,"country":"United States","year":2004,"date":"29/08/2004","sport":"Basketball","gold":1,"silver":0,"bronze":0,"total":1},
  {"athlete":"Rodolfo Rombaldoni","age":27,"country":"Italy","year":2004,"date":"29/08/2004","sport":"Basketball","gold":0,"silver":1,"bronze":0,"total":1},
  {"athlete":"Pepe Sánchez","age":27,"country":"Argentina","year":2004,"date":"29/08/2004","sport":"Basketball","gold":1,"silver":0,"bronze":0,"total":1},
  {"athlete":"Luis Scola","age":24,"country":"Argentina","year":2004,"date":"29/08/2004","sport":"Basketball","gold":1,"silver":0,"bronze":0,"total":1},
  {"athlete":"Hugo Ariel Sconochini","age":33,"country":"Argentina","year":2004,"date":"29/08/2004","sport":"Basketball","gold":1,"silver":0,"bronze":0,"total":1},
  {"athlete":"Tatyana Shchyegoleva","age":22,"country":"Russia","year":2004,"date":"29/08/2004","sport":"Basketball","gold":0,"silver":0,"bronze":1,"total":1},
  {"athlete":"Katie Smith","age":30,"country":"United States","year":2004,"date":"29/08/2004","sport":"Basketball","gold":1,"silver":0,"bronze":0,"total":1},
  {"athlete":"Belinda Snell","age":23,"country":"Australia","year":2004,"date":"29/08/2004","sport":"Basketball","gold":0,"silver":1,"bronze":0,"total":1},
  {"athlete":"Matteo Soragna","age":28,"country":"Italy","year":2004,"date":"29/08/2004","sport":"Basketball","gold":0,"silver":1,"bronze":0,"total":1},
  {"athlete":"Rachael Sporn","age":36,"country":"Australia","year":2004,"date":"29/08/2004","sport":"Basketball","gold":0,"silver":1,"bronze":0,"total":1},
  {"athlete":"Dawn Staley","age":34,"country":"United States","year":2004,"date":"29/08/2004","sport":"Basketball","gold":1,"silver":0,"bronze":0,"total":1},
  {"athlete":"Mariya Stepanova","age":25,"country":"Russia","year":2004,"date":"29/08/2004","sport":"Basketball","gold":0,"silver":0,"bronze":1,"total":1},
  {"athlete":"Amar'e Stoudemire","age":24,"country":"United States","year":2004,"date":"29/08/2004","sport":"Basketball","gold":0,"silver":0,"bronze":1,"total":1},
  {"athlete":"Laura Summerton-Hodges","age":20,"country":"Australia","year":2004,"date":"29/08/2004","sport":"Basketball","gold":0,"silver":1,"bronze":0,"total":1},
  {"athlete":"Sheryl Swoopes","age":33,"country":"United States","year":2004,"date":"29/08/2004","sport":"Basketball","gold":1,"silver":0,"bronze":0,"total":1},
  {"athlete":"Diana Taurasi","age":22,"country":"United States","year":2004,"date":"29/08/2004","sport":"Basketball","gold":1,"silver":0,"bronze":0,"total":1},
  {"athlete":"Penny Taylor","age":23,"country":"Australia","year":2004,"date":"29/08/2004","sport":"Basketball","gold":0,"silver":1,"bronze":0,"total":1},
  {"athlete":"Monique Hennagan","age":24,"country":"United States","year":2000,"date":"01/10/2000","sport":"Athletics","gold":1,"silver":0,"bronze":0,"total":1},
  {"athlete":"Llewellyn Herbert","age":23,"country":"South Africa","year":2000,"date":"01/10/2000","sport":"Athletics","gold":0,"silver":0,"bronze":1,"total":1},
  {"athlete":"Noé Hernández","age":21,"country":"Mexico","year":2000,"date":"01/10/2000","sport":"Athletics","gold":0,"silver":1,"bronze":0,"total":1},
  {"athlete":"Kelly Holmes","age":30,"country":"Great Britain","year":2000,"date":"01/10/2000","sport":"Athletics","gold":0,"silver":0,"bronze":1,"total":1},
  {"athlete":"Olena Hovorova","age":27,"country":"Ukraine","year":2000,"date":"01/10/2000","sport":"Athletics","gold":0,"silver":0,"bronze":1,"total":1},
  {"athlete":"Charmaine Howell","age":25,"country":"Jamaica","year":2000,"date":"01/10/2000","sport":"Athletics","gold":0,"silver":1,"bronze":0,"total":1},
  {"athlete":"Chris Huffins","age":30,"country":"United States","year":2000,"date":"01/10/2000","sport":"Athletics","gold":0,"silver":0,"bronze":1,"total":1},
  {"athlete":"Nick Hysong","age":28,"country":"United States","year":2000,"date":"01/10/2000","sport":"Athletics","gold":1,"silver":0,"bronze":0,"total":1},
  {"athlete":"Susanthika Jayasinghe","age":24,"country":"Sri Lanka","year":2000,"date":"01/10/2000","sport":"Athletics","gold":0,"silver":1,"bronze":0,"total":1},
  {"athlete":"Lawrence Johnson","age":26,"country":"United States","year":2000,"date":"01/10/2000","sport":"Athletics","gold":0,"silver":1,"bronze":0,"total":1},
  {"athlete":"Michael Johnson","age":33,"country":"United States","year":2000,"date":"01/10/2000","sport":"Athletics","gold":1,"silver":0,"bronze":0,"total":1},
  {"athlete":"Marion Jones","age":24,"country":"United States","year":2000,"date":"01/10/2000","sport":"Athletics","gold":1,"silver":0,"bronze":0,"total":1},
  {"athlete":"Denis Kapustin","age":29,"country":"Russia","year":2000,"date":"01/10/2000","sport":"Athletics","gold":0,"silver":0,"bronze":1,"total":1},
  {"athlete":"Anastasia Kelesidou","age":27,"country":"Greece","year":2000,"date":"01/10/2000","sport":"Athletics","gold":0,"silver":1,"bronze":0,"total":1},
  {"athlete":"Kostas Kenteris","age":27,"country":"Greece","year":2000,"date":"01/10/2000","sport":"Athletics","gold":1,"silver":0,"bronze":0,"total":1},
  {"athlete":"Wilson Kipketer","age":29,"country":"Denmark","year":2000,"date":"01/10/2000","sport":"Athletics","gold":0,"silver":1,"bronze":0,"total":1},
  {"athlete":"Sergey Klyugin","age":26,"country":"Russia","year":2000,"date":"01/10/2000","sport":"Athletics","gold":1,"silver":0,"bronze":0,"total":1},
  {"athlete":"Reuben Kosgei","age":21,"country":"Kenya","year":2000,"date":"01/10/2000","sport":"Athletics","gold":1,"silver":0,"bronze":0,"total":1},
  {"athlete":"Olga Kotlyarova","age":24,"country":"Russia","year":2000,"date":"01/10/2000","sport":"Athletics","gold":0,"silver":0,"bronze":1,"total":1},
  {"athlete":"Tatyana Kotova","age":23,"country":"Russia","year":2000,"date":"01/10/2000","sport":"Athletics","gold":0,"silver":0,"bronze":1,"total":1},
  {"athlete":"Frantz Kruger","age":25,"country":"South Africa","year":2000,"date":"01/10/2000","sport":"Athletics","gold":0,"silver":0,"bronze":1,"total":1},
  {"athlete":"Astrid Kumbernuss","age":30,"country":"Germany","year":2000,"date":"01/10/2000","sport":"Athletics","gold":0,"silver":0,"bronze":1,"total":1},
  {"athlete":"Olga Kuzenkova","age":29,"country":"Russia","year":2000,"date":"01/10/2000","sport":"Athletics","gold":0,"silver":1,"bronze":0,"total":1},
  {"athlete":"Bernard Lagat","age":25,"country":"Kenya","year":2000,"date":"01/10/2000","sport":"Athletics","gold":0,"silver":0,"bronze":1,"total":1},
  {"athlete":"Brahim Lahlafi","age":32,"country":"Morocco","year":2000,"date":"01/10/2000","sport":"Athletics","gold":0,"silver":0,"bronze":1,"total":1},
  {"athlete":"Tatyana Lebedeva","age":24,"country":"Russia","year":2000,"date":"01/10/2000","sport":"Athletics","gold":0,"silver":1,"bronze":0,"total":1},
  {"athlete":"Brian Lewis","age":25,"country":"United States","year":2000,"date":"01/10/2000","sport":"Athletics","gold":1,"silver":0,"bronze":0,"total":1},
  {"athlete":"Denise Lewis","age":28,"country":"Great Britain","year":2000,"date":"01/10/2000","sport":"Athletics","gold":1,"silver":0,"bronze":0,"total":1},
  {"athlete":"Vicente Lima","age":23,"country":"Brazil","year":2000,"date":"01/10/2000","sport":"Athletics","gold":0,"silver":1,"bronze":0,"total":1},
  {"athlete":"Sergey Makarov","age":27,"country":"Russia","year":2000,"date":"01/10/2000","sport":"Athletics","gold":0,"silver":0,"bronze":1,"total":1},
  {"athlete":"Mirela Maniani-Tzelili","age":23,"country":"Greece","year":2000,"date":"01/10/2000","sport":"Athletics","gold":0,"silver":1,"bronze":0,"total":1},
  {"athlete":"Tereza Marinova","age":23,"country":"Bulgaria","year":2000,"date":"01/10/2000","sport":"Athletics","gold":1,"silver":0,"bronze":0,"total":1},
  {"athlete":"Fiona May","age":30,"country":"Italy","year":2000,"date":"01/10/2000","sport":"Athletics","gold":0,"silver":1,"bronze":0,"total":1},
  {"athlete":"Freddy Mayola","age":22,"country":"Cuba","year":2000,"date":"01/10/2000","sport":"Athletics","gold":0,"silver":0,"bronze":1,"total":1},
  {"athlete":"Michael McDonald","age":25,"country":"Jamaica","year":2000,"date":"01/10/2000","sport":"Athletics","gold":0,"silver":1,"bronze":0,"total":1},
  {"athlete":"Danny McFarlane","age":28,"country":"Jamaica","year":2000,"date":"01/10/2000","sport":"Athletics","gold":0,"silver":1,"bronze":0,"total":1},
  {"athlete":"Troy McIntosh","age":27,"country":"Bahamas","year":2000,"date":"01/10/2000","sport":"Athletics","gold":0,"silver":0,"bronze":1,"total":1},
  {"athlete":"Osleidys Menéndez","age":20,"country":"Cuba","year":2000,"date":"01/10/2000","sport":"Athletics","gold":0,"silver":0,"bronze":1,"total":1},
  {"athlete":"Noria Mérah-Benida","age":29,"country":"Algeria","year":2000,"date":"01/10/2000","sport":"Athletics","gold":1,"silver":0,"bronze":0,"total":1},
  {"athlete":"Katharine Merry","age":26,"country":"Great Britain","year":2000,"date":"01/10/2000","sport":"Athletics","gold":0,"silver":0,"bronze":1,"total":1},
  {"athlete":"Assefa Mezegebu","age":22,"country":"Ethiopia","year":2000,"date":"01/10/2000","sport":"Athletics","gold":0,"silver":0,"bronze":1,"total":1},
  {"athlete":"Jearl Miles-Clark","age":34,"country":"United States","year":2000,"date":"01/10/2000","sport":"Athletics","gold":1,"silver":0,"bronze":0,"total":1},
  {"athlete":"Avard Moncur","age":21,"country":"Bahamas","year":2000,"date":"01/10/2000","sport":"Athletics","gold":0,"silver":0,"bronze":1,"total":1},
  {"athlete":"Tim Montgomery","age":25,"country":"United States","year":2000,"date":"01/10/2000","sport":"Athletics","gold":1,"silver":0,"bronze":0,"total":1},
  {"athlete":"Jude Monye","age":26,"country":"Nigeria","year":2000,"date":"01/10/2000","sport":"Athletics","gold":1,"silver":0,"bronze":0,"total":1},
  {"athlete":"Melissa Morrison","age":29,"country":"United States","year":2000,"date":"01/10/2000","sport":"Athletics","gold":0,"silver":0,"bronze":1,"total":1},
  {"athlete":"Kirsten Münchow","age":23,"country":"Germany","year":2000,"date":"01/10/2000","sport":"Athletics","gold":0,"silver":0,"bronze":1,"total":1},
  {"athlete":"Tim Munnings","age":34,"country":"Bahamas","year":2000,"date":"01/10/2000","sport":"Athletics","gold":0,"silver":0,"bronze":1,"total":1},
  {"athlete":"Oana Musunoi-Pantelimon","age":28,"country":"Romania","year":2000,"date":"01/10/2000","sport":"Athletics","gold":0,"silver":0,"bronze":1,"total":1},
  {"athlete":"Maria Mutola","age":27,"country":"Mozambique","year":2000,"date":"01/10/2000","sport":"Athletics","gold":1,"silver":0,"bronze":0,"total":1},
  {"athlete":"Nataliya Nazarova","age":21,"country":"Russia","year":2000,"date":"01/10/2000","sport":"Athletics","gold":0,"silver":0,"bronze":1,"total":1},
  {"athlete":"Adam Nelson","age":25,"country":"United States","year":2000,"date":"01/10/2000","sport":"Athletics","gold":0,"silver":1,"bronze":0,"total":1},
  {"athlete":"Noah Ngeny","age":21,"country":"Kenya","year":2000,"date":"01/10/2000","sport":"Athletics","gold":1,"silver":0,"bronze":0,"total":1},
  {"athlete":"Erki Nool","age":30,"country":"Estonia","year":2000,"date":"01/10/2000","sport":"Athletics","gold":1,"silver":0,"bronze":0,"total":1},
  {"athlete":"Sonia O'Sullivan","age":30,"country":"Ireland","year":2000,"date":"01/10/2000","sport":"Athletics","gold":0,"silver":1,"bronze":0,"total":1},
  {"athlete":"Carl Oliver","age":31,"country":"Bahamas","year":2000,"date":"01/10/2000","sport":"Athletics","gold":0,"silver":0,"bronze":1,"total":1},
  {"athlete":"Iván Pedroso","age":27,"country":"Cuba","year":2000,"date":"01/10/2000","sport":"Athletics","gold":1,"silver":0,"bronze":0,"total":1},
  {"athlete":"Larisa Peleshenko","age":36,"country":"Russia","year":2000,"date":"01/10/2000","sport":"Athletics","gold":0,"silver":1,"bronze":0,"total":1},
  {"athlete":"Luis Alberto Pérez","age":31,"country":"Cuba","year":2000,"date":"01/10/2000","sport":"Athletics","gold":0,"silver":0,"bronze":1,"total":1},
  {"athlete":"Nanceen Perry","age":23,"country":"United States","year":2000,"date":"01/10/2000","sport":"Athletics","gold":0,"silver":0,"bronze":1,"total":1},
  {"athlete":"Catherine Pomales-Scott","age":27,"country":"Jamaica","year":2000,"date":"01/10/2000","sport":"Athletics","gold":0,"silver":1,"bronze":0,"total":1},
  {"athlete":"Yelena Prokhorova","age":22,"country":"Russia","year":2000,"date":"01/10/2000","sport":"Athletics","gold":0,"silver":1,"bronze":0,"total":1},
  {"athlete":"Yanina Provalinskaya-Karolchik","age":23,"country":"Belarus","year":2000,"date":"01/10/2000","sport":"Athletics","gold":1,"silver":0,"bronze":0,"total":1},
  {"athlete":"Edson Ribeiro","age":27,"country":"Brazil","year":2000,"date":"01/10/2000","sport":"Athletics","gold":0,"silver":1,"bronze":0,"total":1},
  {"athlete":"Fernanda Ribeiro","age":31,"country":"Portugal","year":2000,"date":"01/10/2000","sport":"Athletics","gold":0,"silver":0,"bronze":1,"total":1},
  {"athlete":"Sandie Richards","age":31,"country":"Jamaica","year":2000,"date":"01/10/2000","sport":"Athletics","gold":0,"silver":1,"bronze":0,"total":1},
  {"athlete":"Passion Richardson","age":25,"country":"United States","year":2000,"date":"01/10/2000","sport":"Athletics","gold":0,"silver":0,"bronze":1,"total":1},
  {"athlete":"Lars Riedel","age":33,"country":"Germany","year":2000,"date":"01/10/2000","sport":"Athletics","gold":0,"silver":1,"bronze":0,"total":1},
  {"athlete":"Djabir Saïd-Guerni","age":23,"country":"Algeria","year":2000,"date":"01/10/2000","sport":"Athletics","gold":0,"silver":0,"bronze":1,"total":1},
  {"athlete":"Ali Saïdi-Sief","age":22,"country":"Algeria","year":2000,"date":"01/10/2000","sport":"Athletics","gold":0,"silver":1,"bronze":0,"total":1},
  {"athlete":"Joel Sánchez","age":36,"country":"Mexico","year":2000,"date":"01/10/2000","sport":"Athletics","gold":0,"silver":0,"bronze":1,"total":1},
  {"athlete":"Natasha Sazanovich","age":27,"country":"Belarus","year":2000,"date":"01/10/2000","sport":"Athletics","gold":0,"silver":0,"bronze":1,"total":1},
  {"athlete":"Nils Schumann","age":22,"country":"Germany","year":2000,"date":"01/10/2000","sport":"Athletics","gold":1,"silver":0,"bronze":0,"total":1},
  {"athlete":"Roman Šebrle","age":25,"country":"Czech Republic","year":2000,"date":"01/10/2000","sport":"Athletics","gold":0,"silver":1,"bronze":0,"total":1},
  {"athlete":"Roman Shchurenko","age":24,"country":"Ukraine","year":2000,"date":"01/10/2000","sport":"Athletics","gold":0,"silver":0,"bronze":1,"total":1},
  {"athlete":"Olga Shishigina","age":31,"country":"Kazakhstan","year":2000,"date":"01/10/2000","sport":"Athletics","gold":1,"silver":0,"bronze":0,"total":1},
  {"athlete":"Lidia Simon","age":27,"country":"Romania","year":2000,"date":"01/10/2000","sport":"Athletics","gold":0,"silver":1,"bronze":0,"total":1},
  {"athlete":"Kamila Skolimowska","age":17,"country":"Poland","year":2000,"date":"01/10/2000","sport":"Athletics","gold":1,"silver":0,"bronze":0,"total":1},
  {"athlete":"Trine Solberg-Hattestad","age":34,"country":"Norway","year":2000,"date":"01/10/2000","sport":"Athletics","gold":1,"silver":0,"bronze":0,"total":1},
  {"athlete":"Yuliya Sotnikova","age":29,"country":"Russia","year":2000,"date":"01/10/2000","sport":"Athletics","gold":0,"silver":0,"bronze":1,"total":1},
  {"athlete":"Javier Sotomayor","age":32,"country":"Cuba","year":2000,"date":"01/10/2000","sport":"Athletics","gold":0,"silver":1,"bronze":0,"total":1},
  {"athlete":"Cláudio Sousa","age":26,"country":"Brazil","year":2000,"date":"01/10/2000","sport":"Athletics","gold":0,"silver":1,"bronze":0,"total":1},
  {"athlete":"Hestrie Storbeck-Cloete","age":22,"country":"South Africa","year":2000,"date":"01/10/2000","sport":"Athletics","gold":0,"silver":1,"bronze":0,"total":1},
  {"athlete":"Chandra Sturrup","age":29,"country":"Bahamas","year":2000,"date":"01/10/2000","sport":"Athletics","gold":1,"silver":0,"bronze":0,"total":1},
  {"athlete":"Naoko Takahashi","age":28,"country":"Japan","year":2000,"date":"01/10/2000","sport":"Athletics","gold":1,"silver":0,"bronze":0,"total":1},
  {"athlete":"Maksim Tarasov","age":29,"country":"Russia","year":2000,"date":"01/10/2000","sport":"Athletics","gold":0,"silver":0,"bronze":1,"total":1},
  {"athlete":"Jai Taurima","age":28,"country":"Australia","year":2000,"date":"01/10/2000","sport":"Athletics","gold":0,"silver":1,"bronze":0,"total":1},
  {"athlete":"Angelo Taylor","age":21,"country":"United States","year":2000,"date":"01/10/2000","sport":"Athletics","gold":1,"silver":0,"bronze":0,"total":1},
  {"athlete":"Paul Tergat","age":31,"country":"Kenya","year":2000,"date":"01/10/2000","sport":"Athletics","gold":0,"silver":1,"bronze":0,"total":1},
  {"athlete":"Aikaterini Thanou","age":25,"country":"Greece","year":2000,"date":"01/10/2000","sport":"Athletics","gold":0,"silver":1,"bronze":0,"total":1},
  {"athlete":"Obadele Thompson","age":24,"country":"Barbados","year":2000,"date":"01/10/2000","sport":"Athletics","gold":0,"silver":0,"bronze":1,"total":1},
  {"athlete":"Tesfaye Tola","age":25,"country":"Ethiopia","year":2000,"date":"01/10/2000","sport":"Athletics","gold":0,"silver":0,"bronze":1,"total":1},
  {"athlete":"Terrence Trammell","age":21,"country":"United States","year":2000,"date":"01/10/2000","sport":"Athletics","gold":0,"silver":1,"bronze":0,"total":1},
  {"athlete":"Derartu Tulu","age":28,"country":"Ethiopia","year":2000,"date":"01/10/2000","sport":"Athletics","gold":1,"silver":0,"bronze":0,"total":1},
  {"athlete":"Kjersti Tysse-Plätzer","age":28,"country":"Norway","year":2000,"date":"01/10/2000","sport":"Athletics","gold":0,"silver":1,"bronze":0,"total":1},
  {"athlete":"Enefiok Udo-Obong","age":18,"country":"Nigeria","year":2000,"date":"01/10/2000","sport":"Athletics","gold":1,"silver":0,"bronze":0,"total":1},
  {"athlete":"María Vascó","age":24,"country":"Spain","year":2000,"date":"01/10/2000","sport":"Athletics","gold":0,"silver":0,"bronze":1,"total":1},
  {"athlete":"Nicola Vizzoni","age":26,"country":"Italy","year":2000,"date":"01/10/2000","sport":"Athletics","gold":0,"silver":1,"bronze":0,"total":1},
  {"athlete":"Eric Wainaina","age":26,"country":"Kenya","year":2000,"date":"01/10/2000","sport":"Athletics","gold":0,"silver":1,"bronze":0,"total":1},
  {"athlete":"Wang Liping","age":24,"country":"China","year":2000,"date":"01/10/2000","sport":"Athletics","gold":1,"silver":0,"bronze":0,"total":1},
  {"athlete":"Bernard Williams III","age":22,"country":"United States","year":2000,"date":"01/10/2000","sport":"Athletics","gold":1,"silver":0,"bronze":0,"total":1},
  {"athlete":"Chris Williams","age":28,"country":"Jamaica","year":2000,"date":"01/10/2000","sport":"Athletics","gold":0,"silver":1,"bronze":0,"total":1},
  {"athlete":"Million Wolde","age":21,"country":"Ethiopia","year":2000,"date":"01/10/2000","sport":"Athletics","gold":1,"silver":0,"bronze":0,"total":1},
  {"athlete":"Irina Yatchenko","age":34,"country":"Belarus","year":2000,"date":"01/10/2000","sport":"Athletics","gold":0,"silver":0,"bronze":1,"total":1},
  {"athlete":"Yelena Yelesina","age":30,"country":"Russia","year":2000,"date":"01/10/2000","sport":"Athletics","gold":1,"silver":0,"bronze":0,"total":1},
  {"athlete":"Jan Železný","age":34,"country":"Czech Republic","year":2000,"date":"01/10/2000","sport":"Athletics","gold":1,"silver":0,"bronze":0,"total":1},
  {"athlete":"Szymon Ziólkowski","age":24,"country":"Poland","year":2000,"date":"01/10/2000","sport":"Athletics","gold":1,"silver":0,"bronze":0,"total":1},
  {"athlete":"Ellina Zvereva","age":39,"country":"Belarus","year":2000,"date":"01/10/2000","sport":"Athletics","gold":1,"silver":0,"bronze":0,"total":1},
  {"athlete":"Olesya Zykina","age":19,"country":"Russia","year":2000,"date":"01/10/2000","sport":"Athletics","gold":0,"silver":0,"bronze":1,"total":1},
  {"athlete":"Didier Défago","age":32,"country":"Switzerland","year":2010,"date":"28/02/2010","sport":"Alpine Skiing","gold":1,"silver":0,"bronze":0,"total":1},
  {"athlete":"Andrea Fischbacher","age":24,"country":"Austria","year":2010,"date":"28/02/2010","sport":"Alpine Skiing","gold":1,"silver":0,"bronze":0,"total":1},
  {"athlete":"Carlo Janka","age":23,"country":"Switzerland","year":2010,"date":"28/02/2010","sport":"Alpine Skiing","gold":1,"silver":0,"bronze":0,"total":1},
  {"athlete":"Kjetil Jansrud","age":24,"country":"Norway","year":2010,"date":"28/02/2010","sport":"Alpine Skiing","gold":0,"silver":1,"bronze":0,"total":1},
  {"athlete":"André Myhrer","age":27,"country":"Sweden","year":2010,"date":"28/02/2010","sport":"Alpine Skiing","gold":0,"silver":0,"bronze":1,"total":1},
  {"athlete":"Anja Pärson","age":28,"country":"Sweden","year":2010,"date":"28/02/2010","sport":"Alpine Skiing","gold":0,"silver":0,"bronze":1,"total":1},
  {"athlete":"Giuliano Razzoli","age":25,"country":"Italy","year":2010,"date":"28/02/2010","sport":"Alpine Skiing","gold":1,"silver":0,"bronze":0,"total":1},
  {"athlete":"Viktoria Rebensburg","age":20,"country":"Germany","year":2010,"date":"28/02/2010","sport":"Alpine Skiing","gold":1,"silver":0,"bronze":0,"total":1},
  {"athlete":"Marlies Schild","age":28,"country":"Austria","year":2010,"date":"28/02/2010","sport":"Alpine Skiing","gold":0,"silver":1,"bronze":0,"total":1},
  {"athlete":"Andrew Weibrecht","age":24,"country":"United States","year":2010,"date":"28/02/2010","sport":"Alpine Skiing","gold":0,"silver":0,"bronze":1,"total":1},
  {"athlete":"Šárka Záhrobská","age":25,"country":"Czech Republic","year":2010,"date":"28/02/2010","sport":"Alpine Skiing","gold":0,"silver":0,"bronze":1,"total":1},
  {"athlete":"Silvan Zurbriggen","age":28,"country":"Switzerland","year":2010,"date":"28/02/2010","sport":"Alpine Skiing","gold":0,"silver":0,"bronze":1,"total":1},
  {"athlete":"Kjetil André Aamodt","age":34,"country":"Norway","year":2006,"date":"26/02/2006","sport":"Alpine Skiing","gold":1,"silver":0,"bronze":0,"total":1},
  {"athlete":"Joël Chenal","age":32,"country":"France","year":2006,"date":"26/02/2006","sport":"Alpine Skiing","gold":0,"silver":1,"bronze":0,"total":1},
  {"athlete":"Antoine Dénériaz","age":29,"country":"France","year":2006,"date":"26/02/2006","sport":"Alpine Skiing","gold":1,"silver":0,"bronze":0,"total":1},
  {"athlete":"Reinfried Herbst","age":27,"country":"Austria","year":2006,"date":"26/02/2006","sport":"Alpine Skiing","gold":0,"silver":1,"bronze":0,"total":1},
  {"athlete":"Ambrosi Hoffmann","age":28,"country":"Switzerland","year":2006,"date":"26/02/2006","sport":"Alpine Skiing","gold":0,"silver":0,"bronze":1,"total":1},
  {"athlete":"Nicole Hosp","age":22,"country":"Austria","year":2006,"date":"26/02/2006","sport":"Alpine Skiing","gold":0,"silver":1,"bronze":0,"total":1},
  {"athlete":"Bruno Kernen","age":33,"country":"Switzerland","year":2006,"date":"26/02/2006","sport":"Alpine Skiing","gold":0,"silver":0,"bronze":1,"total":1},
  {"athlete":"Ivica Kostelic","age":26,"country":"Croatia","year":2006,"date":"26/02/2006","sport":"Alpine Skiing","gold":0,"silver":1,"bronze":0,"total":1},
  {"athlete":"Ted Ligety","age":21,"country":"United States","year":2006,"date":"26/02/2006","sport":"Alpine Skiing","gold":1,"silver":0,"bronze":0,"total":1},
  {"athlete":"Julia Mancuso","age":21,"country":"United States","year":2006,"date":"26/02/2006","sport":"Alpine Skiing","gold":1,"silver":0,"bronze":0,"total":1},
  {"athlete":"Alexandra Meissnitzer","age":32,"country":"Austria","year":2006,"date":"26/02/2006","sport":"Alpine Skiing","gold":0,"silver":0,"bronze":1,"total":1},
  {"athlete":"Anna Ottosson","age":29,"country":"Sweden","year":2006,"date":"26/02/2006","sport":"Alpine Skiing","gold":0,"silver":0,"bronze":1,"total":1},
  {"athlete":"Tanja Poutiainen","age":25,"country":"Finland","year":2006,"date":"26/02/2006","sport":"Alpine Skiing","gold":0,"silver":1,"bronze":0,"total":1},
  {"athlete":"Martina Schild","age":24,"country":"Switzerland","year":2006,"date":"26/02/2006","sport":"Alpine Skiing","gold":0,"silver":1,"bronze":0,"total":1},
  {"athlete":"Michael Walchhofer","age":30,"country":"Austria","year":2006,"date":"26/02/2006","sport":"Alpine Skiing","gold":0,"silver":1,"bronze":0,"total":1},
  {"athlete":"Sébastien Amiez","age":29,"country":"France","year":2002,"date":"24/02/2002","sport":"Alpine Skiing","gold":0,"silver":1,"bronze":0,"total":1},
  {"athlete":"Daniela Ceccarelli","age":26,"country":"Italy","year":2002,"date":"24/02/2002","sport":"Alpine Skiing","gold":1,"silver":0,"bronze":0,"total":1},
  {"athlete":"Martina Ertl-Renz","age":28,"country":"Germany","year":2002,"date":"24/02/2002","sport":"Alpine Skiing","gold":0,"silver":0,"bronze":1,"total":1},
  {"athlete":"Isolde Kostner","age":26,"country":"Italy","year":2002,"date":"24/02/2002","sport":"Alpine Skiing","gold":0,"silver":1,"bronze":0,"total":1},
  {"athlete":"Carole Montillet-Carles","age":28,"country":"France","year":2002,"date":"24/02/2002","sport":"Alpine Skiing","gold":1,"silver":0,"bronze":0,"total":1},
  {"athlete":"Sonja Nef","age":29,"country":"Switzerland","year":2002,"date":"24/02/2002","sport":"Alpine Skiing","gold":0,"silver":0,"bronze":1,"total":1},
  {"athlete":"Laure Pequegnot","age":26,"country":"France","year":2002,"date":"24/02/2002","sport":"Alpine Skiing","gold":0,"silver":1,"bronze":0,"total":1},
  {"athlete":"Karen Putzer","age":23,"country":"Italy","year":2002,"date":"24/02/2002","sport":"Alpine Skiing","gold":0,"silver":0,"bronze":1,"total":1},
  {"athlete":"Andreas Schifferer","age":27,"country":"Austria","year":2002,"date":"24/02/2002","sport":"Alpine Skiing","gold":0,"silver":0,"bronze":1,"total":1},
  {"athlete":"Fritz Strobl","age":29,"country":"Austria","year":2002,"date":"24/02/2002","sport":"Alpine Skiing","gold":1,"silver":0,"bronze":0,"total":1},
  {"athlete":"Jean-Pierre Vidal","age":24,"country":"France","year":2002,"date":"24/02/2002","sport":"Alpine Skiing","gold":1,"silver":0,"bronze":0,"total":1},
  {"athlete":"Mariana Avitia","age":18,"country":"Mexico","year":2012,"date":"12/08/2012","sport":"Archery","gold":0,"silver":0,"bronze":1,"total":1},
  {"athlete":"Cheng Ming","age":26,"country":"China","year":2012,"date":"12/08/2012","sport":"Archery","gold":0,"silver":1,"bronze":0,"total":1},
  {"athlete":"Choi Hyeon-Ju","age":27,"country":"South Korea","year":2012,"date":"12/08/2012","sport":"Archery","gold":1,"silver":0,"bronze":0,"total":1},
  {"athlete":"Dai Xiaoxiang","age":21,"country":"China","year":2012,"date":"12/08/2012","sport":"Archery","gold":0,"silver":0,"bronze":1,"total":1},
  {"athlete":"Brady Ellison","age":23,"country":"United States","year":2012,"date":"12/08/2012","sport":"Archery","gold":0,"silver":1,"bronze":0,"total":1},
  {"athlete":"Fang Yuting","age":22,"country":"China","year":2012,"date":"12/08/2012","sport":"Archery","gold":0,"silver":1,"bronze":0,"total":1},
  {"athlete":"Michele Frangilli","age":36,"country":"Italy","year":2012,"date":"12/08/2012","sport":"Archery","gold":1,"silver":0,"bronze":0,"total":1},
  {"athlete":"Takaharu Furukawa","age":27,"country":"Japan","year":2012,"date":"12/08/2012","sport":"Archery","gold":0,"silver":1,"bronze":0,"total":1},
  {"athlete":"Marco Galiazzo","age":29,"country":"Italy","year":2012,"date":"12/08/2012","sport":"Archery","gold":1,"silver":0,"bronze":0,"total":1},
  {"athlete":"Ren Hayakawa","age":24,"country":"Japan","year":2012,"date":"12/08/2012","sport":"Archery","gold":0,"silver":0,"bronze":1,"total":1},
  {"athlete":"Im Dong-Hyeon","age":27,"country":"South Korea","year":2012,"date":"12/08/2012","sport":"Archery","gold":0,"silver":0,"bronze":1,"total":1},
  {"athlete":"Jake Kaminski","age":23,"country":"United States","year":2012,"date":"12/08/2012","sport":"Archery","gold":0,"silver":1,"bronze":0,"total":1},
  {"athlete":"Miki Kanie","age":23,"country":"Japan","year":2012,"date":"12/08/2012","sport":"Archery","gold":0,"silver":0,"bronze":1,"total":1},
  {"athlete":"Kaori Kawanaka","age":20,"country":"Japan","year":2012,"date":"12/08/2012","sport":"Archery","gold":0,"silver":0,"bronze":1,"total":1},
  {"athlete":"Kim Bub-Min","age":21,"country":"South Korea","year":2012,"date":"12/08/2012","sport":"Archery","gold":0,"silver":0,"bronze":1,"total":1},
  {"athlete":"Lee Seong-Jin","age":27,"country":"South Korea","year":2012,"date":"12/08/2012","sport":"Archery","gold":1,"silver":0,"bronze":0,"total":1},
  {"athlete":"Mauro Nespoli","age":24,"country":"Italy","year":2012,"date":"12/08/2012","sport":"Archery","gold":1,"silver":0,"bronze":0,"total":1},
  {"athlete":"Aída Román","age":24,"country":"Mexico","year":2012,"date":"12/08/2012","sport":"Archery","gold":0,"silver":1,"bronze":0,"total":1},
  {"athlete":"Jacob Wukie","age":26,"country":"United States","year":2012,"date":"12/08/2012","sport":"Archery","gold":0,"silver":1,"bronze":0,"total":1},
  {"athlete":"Xu Jing","age":21,"country":"China","year":2012,"date":"12/08/2012","sport":"Archery","gold":0,"silver":1,"bronze":0,"total":1},
  {"athlete":"Virginie Arnold","age":28,"country":"France","year":2008,"date":"24/08/2008","sport":"Archery","gold":0,"silver":0,"bronze":1,"total":1},
  {"athlete":"Bair Badyonov","age":32,"country":"Russia","year":2008,"date":"24/08/2008","sport":"Archery","gold":0,"silver":0,"bronze":1,"total":1},
  {"athlete":"Chen Ling","age":21,"country":"China","year":2008,"date":"24/08/2008","sport":"Archery","gold":0,"silver":1,"bronze":0,"total":1},
  {"athlete":"Ilario Di Buò","age":51,"country":"Italy","year":2008,"date":"24/08/2008","sport":"Archery","gold":0,"silver":1,"bronze":0,"total":1},
  {"athlete":"Sophie Dodémont","age":34,"country":"France","year":2008,"date":"24/08/2008","sport":"Archery","gold":0,"silver":0,"bronze":1,"total":1},
  {"athlete":"Marco Galiazzo","age":25,"country":"Italy","year":2008,"date":"24/08/2008","sport":"Archery","gold":0,"silver":1,"bronze":0,"total":1},
  {"athlete":"Guo Dan","age":22,"country":"China","year":2008,"date":"24/08/2008","sport":"Archery","gold":0,"silver":1,"bronze":0,"total":1},
  {"athlete":"Im Dong-Hyeon","age":23,"country":"South Korea","year":2008,"date":"24/08/2008","sport":"Archery","gold":1,"silver":0,"bronze":0,"total":1},
  {"athlete":"Jiang Lin","age":26,"country":"China","year":2008,"date":"24/08/2008","sport":"Archery","gold":0,"silver":0,"bronze":1,"total":1},
  {"athlete":"Joo Hyun-Jung","age":26,"country":"South Korea","year":2008,"date":"24/08/2008","sport":"Archery","gold":1,"silver":0,"bronze":0,"total":1},
  {"athlete":"Lee Chang-Hwan","age":26,"country":"South Korea","year":2008,"date":"24/08/2008","sport":"Archery","gold":1,"silver":0,"bronze":0,"total":1},
  {"athlete":"Li Wenquan","age":22,"country":"China","year":2008,"date":"24/08/2008","sport":"Archery","gold":0,"silver":0,"bronze":1,"total":1},
  {"athlete":"Mauro Nespoli","age":20,"country":"Italy","year":2008,"date":"24/08/2008","sport":"Archery","gold":0,"silver":1,"bronze":0,"total":1},
  {"athlete":"Viktor Ruban","age":27,"country":"Ukraine","year":2008,"date":"24/08/2008","sport":"Archery","gold":1,"silver":0,"bronze":0,"total":1},
  {"athlete":"Bérengère Schuh","age":24,"country":"France","year":2008,"date":"24/08/2008","sport":"Archery","gold":0,"silver":0,"bronze":1,"total":1},
  {"athlete":"Xue Haifeng","age":28,"country":"China","year":2008,"date":"24/08/2008","sport":"Archery","gold":0,"silver":0,"bronze":1,"total":1},
  {"athlete":"Chen Li-Ju","age":23,"country":"Chinese Taipei","year":2004,"date":"29/08/2004","sport":"Archery","gold":0,"silver":0,"bronze":1,"total":1},
  {"athlete":"Chen Szu-Yuan","age":23,"country":"Chinese Taipei","year":2004,"date":"29/08/2004","sport":"Archery","gold":0,"silver":1,"bronze":0,"total":1},
  {"athlete":"Tim Cuddihy","age":17,"country":"Australia","year":2004,"date":"29/08/2004","sport":"Archery","gold":0,"silver":0,"bronze":1,"total":1},
  {"athlete":"Marco Galiazzo","age":21,"country":"Italy","year":2004,"date":"29/08/2004","sport":"Archery","gold":1,"silver":0,"bronze":0,"total":1},
  {"athlete":"He Ying","age":27,"country":"China","year":2004,"date":"29/08/2004","sport":"Archery","gold":0,"silver":1,"bronze":0,"total":1},
  {"athlete":"Dmytro Hrachov","age":20,"country":"Ukraine","year":2004,"date":"29/08/2004","sport":"Archery","gold":0,"silver":0,"bronze":1,"total":1},
  {"athlete":"Im Dong-Hyeon","age":19,"country":"South Korea","year":2004,"date":"29/08/2004","sport":"Archery","gold":1,"silver":0,"bronze":0,"total":1},
  {"athlete":"Jang Yong-Ho","age":28,"country":"South Korea","year":2004,"date":"29/08/2004","sport":"Archery","gold":1,"silver":0,"bronze":0,"total":1},
  {"athlete":"Lin Sang","age":26,"country":"China","year":2004,"date":"29/08/2004","sport":"Archery","gold":0,"silver":1,"bronze":0,"total":1},
  {"athlete":"Liu Ming-Huang","age":19,"country":"Chinese Taipei","year":2004,"date":"29/08/2004","sport":"Archery","gold":0,"silver":1,"bronze":0,"total":1},
  {"athlete":"Park Gyeong-Mo","age":28,"country":"South Korea","year":2004,"date":"29/08/2004","sport":"Archery","gold":1,"silver":0,"bronze":0,"total":1},
  {"athlete":"Viktor Ruban","age":23,"country":"Ukraine","year":2004,"date":"29/08/2004","sport":"Archery","gold":0,"silver":0,"bronze":1,"total":1},
  {"athlete":"Oleksandr Serdiuk","age":26,"country":"Ukraine","year":2004,"date":"29/08/2004","sport":"Archery","gold":0,"silver":0,"bronze":1,"total":1},
  {"athlete":"Wang Cheng-Pang","age":17,"country":"Chinese Taipei","year":2004,"date":"29/08/2004","sport":"Archery","gold":0,"silver":1,"bronze":0,"total":1},
  {"athlete":"Alison Williamson","age":32,"country":"Great Britain","year":2004,"date":"29/08/2004","sport":"Archery","gold":0,"silver":0,"bronze":1,"total":1},
  {"athlete":"Wu Hui-Ju","age":21,"country":"Chinese Taipei","year":2004,"date":"29/08/2004","sport":"Archery","gold":0,"silver":0,"bronze":1,"total":1},
  {"athlete":"Hiroshi Yamamoto","age":41,"country":"Japan","year":2004,"date":"29/08/2004","sport":"Archery","gold":0,"silver":1,"bronze":0,"total":1},
  {"athlete":"Yuan Shu-Chi","age":19,"country":"Chinese Taipei","year":2004,"date":"29/08/2004","sport":"Archery","gold":0,"silver":0,"bronze":1,"total":1},
  {"athlete":"Yun Mi-Jin","age":21,"country":"South Korea","year":2004,"date":"29/08/2004","sport":"Archery","gold":1,"silver":0,"bronze":0,"total":1},
  {"athlete":"Zhang Juanjuan","age":23,"country":"China","year":2004,"date":"29/08/2004","sport":"Archery","gold":0,"silver":1,"bronze":0,"total":1},
  {"athlete":"Matteo Bisiani","age":24,"country":"Italy","year":2000,"date":"01/10/2000","sport":"Archery","gold":0,"silver":1,"bronze":0,"total":1},
  {"athlete":"Nataliya Burdeina","age":26,"country":"Ukraine","year":2000,"date":"01/10/2000","sport":"Archery","gold":0,"silver":1,"bronze":0,"total":1},
  {"athlete":"Ilario Di Buò","age":43,"country":"Italy","year":2000,"date":"01/10/2000","sport":"Archery","gold":0,"silver":1,"bronze":0,"total":1},
  {"athlete":"Simon Fairweather","age":30,"country":"Australia","year":2000,"date":"01/10/2000","sport":"Archery","gold":1,"silver":0,"bronze":0,"total":1},
  {"athlete":"Michele Frangilli","age":24,"country":"Italy","year":2000,"date":"01/10/2000","sport":"Archery","gold":0,"silver":1,"bronze":0,"total":1},
  {"athlete":"Jang Yong-Ho","age":24,"country":"South Korea","year":2000,"date":"01/10/2000","sport":"Archery","gold":1,"silver":0,"bronze":0,"total":1},
  {"athlete":"Butch Johnson","age":45,"country":"United States","year":2000,"date":"01/10/2000","sport":"Archery","gold":0,"silver":0,"bronze":1,"total":1},
  {"athlete":"Kim Cheong-Tae","age":20,"country":"South Korea","year":2000,"date":"01/10/2000","sport":"Archery","gold":1,"silver":0,"bronze":0,"total":1},
  {"athlete":"Barbara Mensing","age":39,"country":"Germany","year":2000,"date":"01/10/2000","sport":"Archery","gold":0,"silver":0,"bronze":1,"total":1},
  {"athlete":"O Gyo-Mun","age":28,"country":"South Korea","year":2000,"date":"01/10/2000","sport":"Archery","gold":1,"silver":0,"bronze":0,"total":1},
  {"athlete":"Cornelia Pfohl","age":29,"country":"Germany","year":2000,"date":"01/10/2000","sport":"Archery","gold":0,"silver":0,"bronze":1,"total":1},
  {"athlete":"Olena Sadovnycha","age":32,"country":"Ukraine","year":2000,"date":"01/10/2000","sport":"Archery","gold":0,"silver":1,"bronze":0,"total":1},
  {"athlete":"Kateryna Serdiuk","age":17,"country":"Ukraine","year":2000,"date":"01/10/2000","sport":"Archery","gold":0,"silver":1,"bronze":0,"total":1},
  {"athlete":"Wietse van Alten","age":21,"country":"Netherlands","year":2000,"date":"01/10/2000","sport":"Archery","gold":0,"silver":0,"bronze":1,"total":1},
  {"athlete":"Sandra Wagner-Sachse","age":31,"country":"Germany","year":2000,"date":"01/10/2000","sport":"Archery","gold":0,"silver":0,"bronze":1,"total":1},
  {"athlete":"Rod White","age":23,"country":"United States","year":2000,"date":"01/10/2000","sport":"Archery","gold":0,"silver":0,"bronze":1,"total":1}]